pymxbi/__init__.py
pymxbi/detector/beam_break_rfid_detector.py
pymxbi/detector/detector.py
pymxbi/detector/mock_detector.py
pymxbi/detector/rfid_detector.py
pymxbi/infra/amixer.py
pymxbi/infra/rsync.py
pymxbi/peripheral/pumps/RPI_gpio_pump.py
pymxbi/peripheral/pumps/pump.py
pymxbi/peripheral/rfid/dorset_lid665v42.py
pymxbi/peripheral/rfid/rfid.py
pymxbi/peripheral/through_beam_sensor/RPI_IR_break_beam_sensor.py
pymxbi/peripheral/through_beam_sensor/through_beam_sensor.py
pymxbi/py.typed
pymxbi/rewarder/mock_rewarder.py
pymxbi/rewarder/pump_rewarder.py
pymxbi/rewarder/rewarder.py
pymxbi/tools/setup_samba/setup_samba.py
pymxbi-0.1.1.dist-info/WHEEL
pymxbi-0.1.1.dist-info/entry_points.txt
pymxbi-0.1.1.dist-info/METADATA
pymxbi-0.1.1.dist-info/RECORD
