Metadata-Version: 2.3
Name: pymxbi
Version: 0.1.1
Summary: Python interfaces and drivers for MXBI
Author: HuYang
Author-email: HuYang <huyangcommit@gmail.com>
Requires-Dist: gpiozero>=2.0.1
Requires-Dist: loguru>=0.7.3
Requires-Dist: prompt-toolkit>=3.0.52
Requires-Dist: pymotego>=0.1.3
Requires-Dist: pyserial>=3.5
Requires-Dist: rich>=14.2.0
Requires-Dist: typer>=0.21.1
Requires-Python: >=3.14
